tree_sitter_verilog/__init__.py
tree_sitter_verilog/__init__.pyi
tree_sitter_verilog/_binding.pyd
tree_sitter_verilog/binding.c
tree_sitter_verilog/py.typed
tree_sitter_verilog-1.0.2.dist-info/LICENSE
tree_sitter_verilog-1.0.2.dist-info/METADATA
tree_sitter_verilog-1.0.2.dist-info/WHEEL
tree_sitter_verilog-1.0.2.dist-info/top_level.txt
tree_sitter_verilog-1.0.2.dist-info/RECORD
