Metadata-Version: 2.1
Name: tree-sitter-verilog
Version: 1.0.2
Summary: Verilog grammar for tree-sitter
Author: Aliaksei Chapyzhenka
Author-email: Amaan Qureshi <amaanq12@gmail.com>
License: MIT
Project-URL: Homepage, https://github.com/tree-sitter/tree-sitter-verilog
Keywords: incremental,parsing,tree-sitter,verilog
Classifier: Intended Audience :: Developers
Classifier: License :: OSI Approved :: MIT License
Classifier: Topic :: Software Development :: Compilers
Classifier: Topic :: Text Processing :: Linguistic
Classifier: Typing :: Typed
Requires-Python: >=3.9
License-File: LICENSE
Provides-Extra: core
Requires-Dist: tree-sitter~=0.22; extra == "core"
